kursversorgung_google_sheets/__init__.py
kursversorgung_google_sheets/authenticate.py
kursversorgung_google_sheets/kursversorgung.py
kursversorgung_google_sheets/kursversorgung_functions.py
kursversorgung_google_sheets/reports_daily.py
kursversorgung_google_sheets/reports_monthly.py
kursversorgung_google_sheets/software_update.ico
kursversorgung_google_sheets/test.py
kursversorgung_google_sheets-0.1.8.dist-info/LICENSE.txt
kursversorgung_google_sheets-0.1.8.dist-info/METADATA
kursversorgung_google_sheets-0.1.8.dist-info/WHEEL
kursversorgung_google_sheets-0.1.8.dist-info/top_level.txt
kursversorgung_google_sheets-0.1.8.dist-info/RECORD
