Metadata-Version: 2.1
Name: kursversorgung-google-sheets
Version: 0.1.8
Summary: Kursversorgung Google Sheets
Home-page: UNKNOWN
Author: Valentin Baier
Author-email: valentin_baier@gmx.de
License: UNKNOWN
Keywords: python,kursversorgung,warrants,updateLast,updateSecurityName,updateLastSplits
Platform: UNKNOWN
Classifier: Development Status :: 1 - Planning
Classifier: Intended Audience :: Developers
Classifier: Programming Language :: Python :: 3
Classifier: Operating System :: Unix
Classifier: Operating System :: MacOS :: MacOS X
Classifier: Operating System :: Microsoft :: Windows
License-File: LICENSE.txt
Requires-Dist: exchangelib
Requires-Dist: setuptools
Requires-Dist: gspread
Requires-Dist: pandas
Requires-Dist: oauth2client
Requires-Dist: pretty-html-table
Requires-Dist: google-api-python-client
Requires-Dist: bs4
Requires-Dist: beautifulsoup4
Requires-Dist: blpapi
Requires-Dist: xbbg
Requires-Dist: future
Requires-Dist: tzdata
